sqlsy/__init__.py
sqlsy/__main__.py
sqlsy/engine.py
sqlsy/schema.py
sqlsy/utils/__init__.py
sqlsy/utils/custom_callbacks.py
sqlsy/utils/mapping.py
sqlsy-1.1.0.dist-info/METADATA
sqlsy-1.1.0.dist-info/WHEEL
sqlsy-1.1.0.dist-info/entry_points.txt
sqlsy-1.1.0.dist-info/top_level.txt
sqlsy-1.1.0.dist-info/RECORD
