Metadata-Version: 2.1
Name: sqlsy
Version: 1.1.0
Summary: Fill your database Quickly with dummy data
Author-email: shoaib wani <shoaibwani010@gmail.com>
Project-URL: Homepage, https://github.com/pyloris/sqlsy
Keywords: sql,sql dummy data,fake data
Classifier: License :: OSI Approved :: MIT License
Classifier: Operating System :: OS Independent
Classifier: Programming Language :: Python :: 3.11
Classifier: Topic :: Database
Requires-Python: >=3.9
Requires-Dist: mysql-connector-python
Requires-Dist: faker
Requires-Dist: rich
Requires-Dist: termcolor
Requires-Dist: numpy
